odoo/addons/storage_image/README.rst
odoo/addons/storage_image/__init__.py
odoo/addons/storage_image/__manifest__.py
odoo/addons/storage_image/data/ir_config_parameter.xml
odoo/addons/storage_image/i18n/it.po
odoo/addons/storage_image/i18n/storage_image.pot
odoo/addons/storage_image/models/__init__.py
odoo/addons/storage_image/models/storage_file.py
odoo/addons/storage_image/models/storage_image.py
odoo/addons/storage_image/models/storage_image_relation_abstract.py
odoo/addons/storage_image/readme/CONTRIBUTORS.rst
odoo/addons/storage_image/readme/DESCRIPTION.rst
odoo/addons/storage_image/security/ir.model.access.csv
odoo/addons/storage_image/security/ir_rule.xml
odoo/addons/storage_image/security/res_group.xml
odoo/addons/storage_image/static/description/icon.png
odoo/addons/storage_image/static/description/index.html
odoo/addons/storage_image/static/src/css/FieldStorageImageHandle.scss
odoo/addons/storage_image/static/src/js/FieldStorageImageHandle.js
odoo/addons/storage_image/tests/__init__.py
odoo/addons/storage_image/tests/common.py
odoo/addons/storage_image/tests/test_storage_image.py
odoo/addons/storage_image/tests/test_storage_replace_file.py
odoo/addons/storage_image/tests/static/akretion-logo.png
odoo/addons/storage_image/tests/static/oca.png
odoo/addons/storage_image/views/assets.xml
odoo/addons/storage_image/views/storage_image.xml
odoo/addons/storage_image/views/storage_image_relation_abstract.xml
odoo/addons/storage_image/wizards/__init__.py
odoo/addons/storage_image/wizards/replace_file.py
odoo/addons/storage_image/wizards/replace_file.xml
odoo14_addon_storage_image-14.0.2.3.1.dist-info/METADATA
odoo14_addon_storage_image-14.0.2.3.1.dist-info/WHEEL
odoo14_addon_storage_image-14.0.2.3.1.dist-info/top_level.txt
odoo14_addon_storage_image-14.0.2.3.1.dist-info/RECORD
