Metadata-Version: 2.1
Name: odoo14-addon-storage_image
Version: 14.0.2.3.1
Summary: Store image and resized image in a storage backend
Home-page: https://github.com/OCA/storage
Author: Akretion, Odoo Community Association (OCA)
Author-email: support@odoo-community.org
License: LGPL-3
Classifier: Programming Language :: Python
Classifier: Framework :: Odoo
Classifier: Framework :: Odoo :: 14.0
Classifier: License :: OSI Approved :: GNU Lesser General Public License v3 (LGPLv3)
Classifier: Development Status :: 5 - Production/Stable
Requires-Python: >=3.6
Requires-Dist: odoo14-addon-storage-thumbnail
Requires-Dist: odoo<14.1dev,>=14.0a
